Fireflink_NLP/README.md
Fireflink_NLP/__init__.py
Fireflink_NLP/logging_config.py
Fireflink_NLP/utils.py
Fireflink_NLP/agent/prompts.py
Fireflink_NLP/agent/service.py
Fireflink_NLP/agent/views.py
Fireflink_NLP/agent/message_manager/service.py
Fireflink_NLP/agent/message_manager/tests.py
Fireflink_NLP/agent/message_manager/views.py
Fireflink_NLP/browser/FFelement.js
Fireflink_NLP/browser/browser.py
Fireflink_NLP/browser/context.py
Fireflink_NLP/browser/views.py
Fireflink_NLP/controller/service.py
Fireflink_NLP/controller/views.py
Fireflink_NLP/controller/registry/service.py
Fireflink_NLP/controller/registry/views.py
Fireflink_NLP/dom/__init__.py
Fireflink_NLP/dom/buildDomTree.js
Fireflink_NLP/dom/service.py
Fireflink_NLP/dom/views.py
Fireflink_NLP/dom/history_tree_processor/service.py
Fireflink_NLP/dom/history_tree_processor/view.py
fireflink_nlp-1.0.0.dist-info/METADATA
fireflink_nlp-1.0.0.dist-info/WHEEL
fireflink_nlp-1.0.0.dist-info/licenses/LICENSE
fireflink_nlp-1.0.0.dist-info/RECORD
